qudpy/Classes.py
qudpy/__init__.py
qudpy/plot_functions.py
qudpy-1.2.0.dist-info/LICENSE
qudpy-1.2.0.dist-info/METADATA
qudpy-1.2.0.dist-info/WHEEL
qudpy-1.2.0.dist-info/top_level.txt
qudpy-1.2.0.dist-info/RECORD
