Metadata-Version: 2.1
Name: qudpy
Version: 1.2.0
Summary: Nonlinear spectroscopy with quantum dynamics support with Qutip
Author-email: "Syed A. Shah" <alamdar114@gmail.com>
License: MIT License        
Project-URL: Homepage, https://github.com/sa-shah/QuDPy.git
Keywords: Nonlinear Spectroscopy,Quantum Dynamics,Spectroscopic Response
Classifier: Intended Audience :: Science/Research
Classifier: License :: OSI Approved :: MIT License
Classifier: Programming Language :: Python :: 3 :: Only
Classifier: Topic :: Scientific/Engineering
License-File: LICENSE
Requires-Dist: qutip
Requires-Dist: ufss
Requires-Dist: matplotlib
Requires-Dist: numpy
